{
  "resolvedId": "C:/Users/user/Desktop/portfolio/node_modules/tsparticles-engine/esm/Utils/EventDispatcher.js",
  "transforms": [
    {
      "name": "vite:load-fallback",
      "result": "export class EventDispatcher {\n    constructor() {\n        this._listeners = new Map();\n    }\n    addEventListener(type, listener) {\n        this.removeEventListener(type, listener);\n        let arr = this._listeners.get(type);\n        if (!arr) {\n            arr = [];\n            this._listeners.set(type, arr);\n        }\n        arr.push(listener);\n    }\n    dispatchEvent(type, args) {\n        const listeners = this._listeners.get(type);\n        listeners && listeners.forEach((handler) => handler(args));\n    }\n    hasEventListener(type) {\n        return !!this._listeners.get(type);\n    }\n    removeAllEventListeners(type) {\n        if (!type) {\n            this._listeners = new Map();\n        }\n        else {\n            this._listeners.delete(type);\n        }\n    }\n    removeEventListener(type, listener) {\n        const arr = this._listeners.get(type);\n        if (!arr) {\n            return;\n        }\n        const length = arr.length, idx = arr.indexOf(listener);\n        if (idx < 0) {\n            return;\n        }\n        if (length === 1) {\n            this._listeners.delete(type);\n        }\n        else {\n            arr.splice(idx, 1);\n        }\n    }\n}\n",
      "start": 1702665912749,
      "end": 1702665912838,
      "sourcemaps": null
    },
    {
      "name": "nuxt:layer-aliasing",
      "start": 1702665912838,
      "end": 1702665912838,
      "order": "pre"
    },
    {
      "name": "nuxt:server-devonly:transform",
      "start": 1702665912839,
      "end": 1702665912839,
      "order": "pre"
    },
    {
      "name": "nuxt:client-fallback-auto-id",
      "start": 1702665912839,
      "end": 1702665912839,
      "order": "pre"
    },
    {
      "name": "vite:css",
      "start": 1702665912839,
      "end": 1702665912839,
      "order": "normal"
    },
    {
      "name": "vite:esbuild",
      "start": 1702665912839,
      "end": 1702665912839,
      "order": "normal"
    },
    {
      "name": "vite:json",
      "start": 1702665912839,
      "end": 1702665912839,
      "order": "normal"
    },
    {
      "name": "vite:worker",
      "start": 1702665912839,
      "end": 1702665912839,
      "order": "normal"
    },
    {
      "name": "vite:vue",
      "start": 1702665912839,
      "end": 1702665912839,
      "order": "normal"
    },
    {
      "name": "vite:vue-jsx",
      "start": 1702665912839,
      "end": 1702665912839,
      "order": "normal"
    },
    {
      "name": "replace",
      "start": 1702665912839,
      "end": 1702665912839,
      "order": "normal"
    },
    {
      "name": "nuxt:remove-plugin-metadata",
      "start": 1702665912839,
      "end": 1702665912839,
      "order": "normal"
    },
    {
      "name": "nuxt:chunk-error",
      "start": 1702665912839,
      "end": 1702665912839,
      "order": "normal"
    },
    {
      "name": "nuxt:components:imports",
      "start": 1702665912839,
      "end": 1702665912840,
      "order": "normal"
    },
    {
      "name": "replace",
      "start": 1702665912840,
      "end": 1702665912840,
      "order": "normal"
    },
    {
      "name": "ssr-styles",
      "start": 1702665912840,
      "end": 1702665912840,
      "order": "normal"
    },
    {
      "name": "vite:define",
      "start": 1702665912840,
      "end": 1702665912840,
      "order": "normal"
    },
    {
      "name": "vite:css-post",
      "start": 1702665912840,
      "end": 1702665912840,
      "order": "normal"
    },
    {
      "name": "vite:build-html",
      "start": 1702665912840,
      "end": 1702665912840,
      "order": "normal"
    },
    {
      "name": "vite:worker-import-meta-url",
      "start": 1702665912840,
      "end": 1702665912840,
      "order": "normal"
    },
    {
      "name": "vite:asset-import-meta-url",
      "start": 1702665912840,
      "end": 1702665912840,
      "order": "normal"
    },
    {
      "name": "commonjs",
      "start": 1702665912840,
      "end": 1702665912840,
      "order": "normal"
    },
    {
      "name": "vite:dynamic-import-vars",
      "start": 1702665912840,
      "end": 1702665912840,
      "order": "normal"
    },
    {
      "name": "vite:import-glob",
      "start": 1702665912841,
      "end": 1702665912841,
      "order": "normal"
    },
    {
      "name": "nuxt:composable-keys",
      "start": 1702665912841,
      "end": 1702665912841,
      "order": "post"
    },
    {
      "name": "nuxt:imports-transform",
      "start": 1702665912841,
      "end": 1702665912841,
      "order": "post"
    },
    {
      "name": "unctx:transform",
      "start": 1702665912841,
      "end": 1702665912841,
      "order": "post"
    },
    {
      "name": "nuxt:pages-macros-transform",
      "start": 1702665912841,
      "end": 1702665912841,
      "order": "post"
    },
    {
      "name": "nuxt:runtime-paths-dep",
      "start": 1702665912841,
      "end": 1702665912841,
      "order": "post"
    },
    {
      "name": "nuxt:route-injection-plugin",
      "start": 1702665912841,
      "end": 1702665912841,
      "order": "post"
    },
    {
      "name": "nuxt:components-loader",
      "start": 1702665912841,
      "end": 1702665912841,
      "order": "post"
    },
    {
      "name": "nuxt:tree-shake-composables:transform",
      "start": 1702665912841,
      "end": 1702665912841,
      "order": "post"
    },
    {
      "name": "vite:build-import-analysis",
      "start": 1702665912841,
      "end": 1702665912841,
      "order": "normal"
    },
    {
      "name": "vite:reporter",
      "start": 1702665912841,
      "end": 1702665912841,
      "order": "normal"
    }
  ]
}
